[
    {
        "time": 1441.84,
        "text": "English language and"
    },
    {
        "time": 1445.52,
        "text": "This chart also gives you an example of"
    },
    {
        "time": 1449.12,
        "text": "A word"
    },
    {
        "time": 1450.159,
        "text": "Where they occur so"
    },
    {
        "time": 1453.6,
        "text": "Look at this look at some of them at"
    },
    {
        "time": 1455.6,
        "text": "Least"
    },
    {
        "time": 1456.84,
        "text": "Pit it has"
    },
    {
        "time": 1459.76,
        "text": "A vowel e short e"
    },
    {
        "time": 1463.679,
        "text": "Pet and these"
    },
    {
        "time": 1467.44,
        "text": "Sounds are underlined in these words pat"
    },
    {
        "time": 1498.84,
        "text": "Burn burn"
    },
    {
        "time": 1503.2,
        "text": "Born boone bite"
    },
    {
        "time": 1508.24,
        "text": "Bait boy"
    },
    {
        "time": 1512.08,
        "text": "Toe house poor"
    },
    {
        "time": 1515.52,
        "text": "Ear air"
    },
    {
        "time": 1518.64,
        "text": "These are 20"
    },
    {
        "time": 1521.84,
        "text": "Vowel sounds in english language"
    },
    {
        "time": 1527.36,
        "text": "Please look at this chart this"
    },
    {
        "time": 1530.4,
        "text": "Uh these examples carefully and"
    },
    {
        "time": 1533.679,
        "text": "Read them several times"
    },
    {
        "time": 1536.799,
        "text": "These examples pay attention to these"
    },
    {
        "time": 1541.76,
        "text": "Sounds in these words"
    },
    {
        "time": 1544.08,
        "text": "What it will do is it will"
    },
    {
        "time": 1548.4,
        "text": "Get you think about vowel sounds"
    },
    {
        "time": 1551.6,
        "text": "In remaining words that you know vowel"
    },
    {
        "time": 1554.799,
        "text": "Sounds"
    },
    {
        "time": 1555.36,
        "text": "In other words that you will speak"
    },
    {
        "time": 1559.039,
        "text": "Other than these what you must"
    },
    {
        "time": 1562.72,
        "text": "Also do is find another"
    },
    {
        "time": 1567.919,
        "text": "Five words at least"
    },
    {
        "time": 1571.039,
        "text": "For each one of these vowel sounds"
    },
    {
        "time": 1574.32,
        "text": "So that means you i'm asking you to make"
    },
    {
        "time": 1577.36,
        "text": "A list of"
    },
    {
        "time": 1578.159,
        "text": "Hundred english words"
    },
    {
        "time": 1582.24,
        "text": "Where five five"
    },
    {
        "time": 1585.52,
        "text": "Examples for each one of these vowel"
    },
    {
        "time": 1588.159,
        "text": "Sounds"
    },
    {
        "time": 1590.48,
        "text": "You don't have to do that in one go you"
    },
    {
        "time": 1593.039,
        "text": "Don't have to do that"
    },
    {
        "time": 1594.08,
        "text": "In one day but if you can come up with a"
    },
    {
        "time": 1598.72,
        "text": "Set of 20 words 20"
    },
    {
        "time": 1602.24,
        "text": "Different words five times for each one"
    },
    {
        "time": 1605.44,
        "text": "Of these"
    },
    {
        "time": 1606.32,
        "text": "20 vowels you'll get an idea of how"
    },
    {
        "time": 1609.919,
        "text": "Vowel sounds work if"
    },
    {
        "time": 1613.44,
        "text": "Five sets sound too much start with one"
    },
    {
        "time": 1618.08,
        "text": "And then try to pay attention to"
    }
]